README.rst
setup.cfg
setup.py
./__init__.py
./sqlite3worker.py
./sqlite3worker_test.py
sqlite3worker.egg-info/PKG-INFO
sqlite3worker.egg-info/SOURCES.txt
sqlite3worker.egg-info/dependency_links.txt
sqlite3worker.egg-info/top_level.txt