Metadata-Version: 1.1
Name: sqlite3worker
Version: 1.1.6
Summary: ('Thread safe sqlite3 interface',)
Home-page: https://github.com/dashawn888/sqlite3worker
Author: Shawn Lee
Author-email: dashawn@gmail.com
License: UNKNOWN
Keywords: sqlite,sqlite3,thread,multithread,multithreading
Platform: UNKNOWN
Classifier: Development Status :: 5 - Production/Stable
Classifier: Intended Audience :: Developers
Classifier: License :: OSI Approved :: MIT License
Classifier: Programming Language :: Python :: 2
Classifier: Programming Language :: Python :: 2.7
Classifier: Programming Language :: Python :: 3
Classifier: Programming Language :: Python :: 3.0
Classifier: Programming Language :: Python :: 3.1
Classifier: Programming Language :: Python :: 3.2
Classifier: Programming Language :: Python :: 3.3
Classifier: Programming Language :: Python :: 3.4
Classifier: Programming Language :: Python :: 3.5
Classifier: Programming Language :: Python :: 3.6
Classifier: Topic :: Database
